django_admin_action_forms/__init__.py
django_admin_action_forms/admin.py
django_admin_action_forms/apps.py
django_admin_action_forms/decorators.py
django_admin_action_forms/forms.py
django_admin_action_forms/formsets.py
django_admin_action_forms/options.py
django_admin_action_forms/urls.py
django_admin_action_forms/views.py
django_admin_action_forms/widgets.py
django_admin_action_forms/locale/de/LC_MESSAGES/django.mo
django_admin_action_forms/locale/de/LC_MESSAGES/django.po
django_admin_action_forms/locale/en/LC_MESSAGES/django.mo
django_admin_action_forms/locale/en/LC_MESSAGES/django.po
django_admin_action_forms/locale/es/LC_MESSAGES/django.mo
django_admin_action_forms/locale/es/LC_MESSAGES/django.po
django_admin_action_forms/locale/fr/LC_MESSAGES/django.mo
django_admin_action_forms/locale/fr/LC_MESSAGES/django.po
django_admin_action_forms/locale/it/LC_MESSAGES/django.mo
django_admin_action_forms/locale/it/LC_MESSAGES/django.po
django_admin_action_forms/locale/nl/LC_MESSAGES/django.mo
django_admin_action_forms/locale/nl/LC_MESSAGES/django.po
django_admin_action_forms/locale/pl/LC_MESSAGES/django.mo
django_admin_action_forms/locale/pl/LC_MESSAGES/django.po
django_admin_action_forms/locale/pt/LC_MESSAGES/django.mo
django_admin_action_forms/locale/pt/LC_MESSAGES/django.po
django_admin_action_forms/locale/ru/LC_MESSAGES/django.mo
django_admin_action_forms/locale/ru/LC_MESSAGES/django.po
django_admin_action_forms/locale/sv/LC_MESSAGES/django.mo
django_admin_action_forms/locale/sv/LC_MESSAGES/django.po
django_admin_action_forms/static/django_admin_action_forms/css/action_form.css
django_admin_action_forms/static/django_admin_action_forms/js/action_form_autocomplete.js
django_admin_action_forms/templates/django_admin_action_forms/action_form.html
django_admin_action_forms/templates/django_admin_action_forms/inlines/stacked.html
django_admin_action_forms/templates/django_admin_action_forms/inlines/tabular.html
django_admin_action_forms-2.2.0.dist-info/licenses/LICENSE
django_admin_action_forms-2.2.0.dist-info/METADATA
django_admin_action_forms-2.2.0.dist-info/WHEEL
django_admin_action_forms-2.2.0.dist-info/top_level.txt
django_admin_action_forms-2.2.0.dist-info/RECORD
