Metadata-Version: 2.4
Name: django-admin-action-forms
Version: 2.2.0
Summary: Extension for the Django admin panel that allows passing additional parameters to actions by creating intermediate pages with forms.
Author: Michał Pokusa
Maintainer: Michał Pokusa
Project-URL: Repository, https://github.com/michalpokusa/django-admin-action-forms
Project-URL: Changelog, https://github.com/michalpokusa/django-admin-action-forms/blob/main/CHANGELOG.md
Keywords: django,admin,action,actions,form,forms,pass,intermediate,args,arguments,params,parameters,inline,inlines,formset,formsets
Classifier: Development Status :: 5 - Production/Stable
Classifier: Environment :: Web Environment
Classifier: Framework :: Django :: 3.2
Classifier: Framework :: Django :: 4.0
Classifier: Framework :: Django :: 4.1
Classifier: Framework :: Django :: 4.2
Classifier: Framework :: Django :: 4
Classifier: Framework :: Django :: 5.0
Classifier: Framework :: Django :: 5.1
Classifier: Framework :: Django :: 5.2
Classifier: Framework :: Django :: 5
Classifier: Intended Audience :: Developers
Classifier: Operating System :: OS Independent
Classifier: Programming Language :: Python :: 3 :: Only
Classifier: Programming Language :: Python :: 3.10
Classifier: Programming Language :: Python :: 3.11
Classifier: Programming Language :: Python :: 3.12
Classifier: Programming Language :: Python :: 3.6
Classifier: Programming Language :: Python :: 3.7
Classifier: Programming Language :: Python :: 3.8
Classifier: Programming Language :: Python :: 3.9
Classifier: Programming Language :: Python :: 3
Classifier: Programming Language :: Python
Classifier: Topic :: Software Development :: Libraries :: Python Modules
License-File: LICENSE
Requires-Dist: django>=3.2
Dynamic: license-file
